sphinxcontrib/__init__.py
sphinxcontrib/needs_capri/__init__.py
sphinxcontrib/needs_capri/needs_capri.py
sphinxcontrib/needs_capri/service/__init__.py
sphinxcontrib/needs_capri/service/codebeamer.py
sphinxcontrib/needs_capri/service/config.py
sphinx_needs_capri-0.1.0.dist-info/LICENSE
sphinx_needs_capri-0.1.0.dist-info/WHEEL
sphinx_needs_capri-0.1.0.dist-info/METADATA
sphinx_needs_capri-0.1.0.dist-info/RECORD
