Metadata-Version: 2.1
Name: sphinx-needs-capri
Version: 0.1.0
Summary: Synchronize codebeamer with Sphinx-Needs
Home-page: http://github.com/useblocks/sphinx-needs-capri
License: BSL 1.1
Author: team useblocks
Author-email: info@useblocks.com
Requires-Python: >=3.6,<4.0
Classifier: Development Status :: 3 - Alpha
Classifier: Framework :: Sphinx :: Extension
Classifier: Intended Audience :: Developers
Classifier: License :: Other/Proprietary License
Classifier: Operating System :: OS Independent
Classifier: Programming Language :: Python
Classifier: Programming Language :: Python :: 3
Classifier: Programming Language :: Python :: 3.6
Classifier: Programming Language :: Python :: 3.7
Classifier: Programming Language :: Python :: 3.8
Classifier: Programming Language :: Python :: 3.9
Classifier: Topic :: Documentation
Classifier: Topic :: Utilities
Provides-Extra: docs
Requires-Dist: sphinx-needs-extensions (>=0.1.0,<0.2.0)
Requires-Dist: sphinxcontrib-needs (>=0.7,<0.8)
Project-URL: Documentation, https://sphinx-needs-capri.readthedocs.io/en/latest/
Project-URL: Repository, http://github.com/useblocks/sphinx-needs-capri
